{
  "__elements": [],
  "annotations": {
    "list": [
      {
        "builtIn": 1,
        "datasource": {
          "type": "datasource",
          "uid": "grafana"
        },
        "enable": true,
        "hide": true,
        "iconColor": "rgba(0, 211, 255, 1)",
        "name": "Annotations & Alerts",
        "target": {
          "limit": 100,
          "matchAny": false,
          "tags": [],
          "type": "dashboard"
        },
        "type": "dashboard"
      }
    ]
  },
  "editable": true,
  "fiscalYearStartMonth": 0,
  "graphTooltip": 0,
  "id": null,
  "iteration": 1659090580950,
  "links": [],
  "liveNow": false,
  "panels": [
    {
      "collapsed": true,
      "datasource": {
        "type": "prometheus",
        "uid": "prometheus"
      },
      "gridPos": {
        "h": 1,
        "w": 24,
        "x": 0,
        "y": 0
      },
      "id": 22,
      "panels": [
        {
          "aliasColors": {},
          "bars": false,
          "dashLength": 10,
          "dashes": false,
          "datasource": {
            "type": "prometheus",
            "uid": "prometheus"
          },
          "fieldConfig": {
            "defaults": {
              "links": []
            },
            "overrides": []
          },
          "fill": 1,
          "fillGradient": 0,
          "gridPos": {
            "h": 11,
            "w": 12,
            "x": 0,
            "y": 1
          },
          "hiddenSeries": false,
          "id": 18,
          "legend": {
            "alignAsTable": false,
            "avg": false,
            "current": false,
            "max": false,
            "min": false,
            "rightSide": false,
            "show": false,
            "total": false,
            "values": false
          },
          "lines": true,
          "linewidth": 1,
          "links": [],
          "nullPointMode": "null",
          "options": {
            "alertThreshold": true
          },
          "percentage": false,
          "pluginVersion": "9.0.2",
          "pointradius": 2,
          "points": false,
          "renderer": "flot",
          "seriesOverrides": [],
          "spaceLength": 10,
          "stack": false,
          "steppedLine": false,
          "targets": [
            {
              "datasource": {
                "type": "prometheus",
                "uid": "prometheus"
              },
              "expr": "process_resident_memory_bytes{instance=\"$instance\"}",
              "interval": "",
              "intervalFactor": 1,
              "legendFormat": "",
              "refId": "A"
            }
          ],
          "thresholds": [],
          "timeRegions": [],
          "title": "Process Mem Usage",
          "tooltip": {
            "shared": true,
            "sort": 0,
            "value_type": "individual"
          },
          "transparent": true,
          "type": "graph",
          "xaxis": {
            "mode": "time",
            "show": true,
            "values": []
          },
          "yaxes": [
            {
              "format": "decbytes",
              "logBase": 1,
              "show": true
            },
            {
              "format": "short",
              "logBase": 1,
              "show": true
            }
          ],
          "yaxis": {
            "align": false
          }
        },
        {
          "aliasColors": {},
          "bars": false,
          "dashLength": 10,
          "dashes": false,
          "datasource": {
            "type": "prometheus",
            "uid": "prometheus"
          },
          "fieldConfig": {
            "defaults": {
              "links": []
            },
            "overrides": []
          },
          "fill": 1,
          "fillGradient": 0,
          "gridPos": {
            "h": 11,
            "w": 12,
            "x": 12,
            "y": 1
          },
          "hiddenSeries": false,
          "id": 20,
          "legend": {
            "avg": false,
            "current": false,
            "max": false,
            "min": false,
            "show": false,
            "total": false,
            "values": false
          },
          "lines": true,
          "linewidth": 1,
          "nullPointMode": "null",
          "options": {
            "alertThreshold": true
          },
          "percentage": false,
          "pluginVersion": "9.0.2",
          "pointradius": 2,
          "points": false,
          "renderer": "flot",
          "seriesOverrides": [],
          "spaceLength": 10,
          "stack": false,
          "steppedLine": false,
          "targets": [
            {
              "datasource": {
                "type": "prometheus",
                "uid": "prometheus"
              },
              "expr": "rate(process_cpu_seconds_total{instance=\"$instance\"}[$__interval])*100",
              "interval": "",
              "intervalFactor": 2,
              "legendFormat": "",
              "refId": "A"
            }
          ],
          "thresholds": [],
          "timeRegions": [],
          "title": "Process CPU Usage",
          "tooltip": {
            "shared": true,
            "sort": 0,
            "value_type": "individual"
          },
          "transparent": true,
          "type": "graph",
          "xaxis": {
            "mode": "time",
            "show": true,
            "values": []
          },
          "yaxes": [
            {
              "format": "percent",
              "logBase": 1,
              "show": true
            },
            {
              "format": "short",
              "logBase": 1,
              "show": true
            }
          ],
          "yaxis": {
            "align": false
          }
        },
        {
          "datasource": {
            "type": "prometheus",
            "uid": "prometheus"
          },
          "fieldConfig": {
            "defaults": {
              "color": {
                "mode": "thresholds"
              },
              "mappings": [
                {
                  "options": {
                    "match": "null",
                    "result": {
                      "text": "N/A"
                    }
                  },
                  "type": "special"
                }
              ],
              "thresholds": {
                "mode": "absolute",
                "steps": [
                  {
                    "color": "green"
                  },
                  {
                    "color": "red",
                    "value": 80
                  }
                ]
              },
              "unit": "dateTimeAsIso"
            },
            "overrides": []
          },
          "gridPos": {
            "h": 9,
            "w": 5,
            "x": 0,
            "y": 12
          },
          "id": 16,
          "links": [],
          "maxDataPoints": 100,
          "options": {
            "colorMode": "none",
            "graphMode": "none",
            "justifyMode": "auto",
            "orientation": "horizontal",
            "reduceOptions": {
              "calcs": ["lastNotNull"],
              "fields": "",
              "values": false
            },
            "text": {},
            "textMode": "auto"
          },
          "pluginVersion": "9.0.2",
          "targets": [
            {
              "datasource": {
                "type": "prometheus",
                "uid": "prometheus"
              },
              "expr": "(process_start_time_seconds{instance=\"$instance\"})*1000",
              "instant": false,
              "interval": "",
              "intervalFactor": 1,
              "legendFormat": "",
              "refId": "A"
            }
          ],
          "title": "Up Since",
          "transparent": true,
          "type": "stat"
        }
      ],
      "targets": [
        {
          "datasource": {
            "type": "prometheus",
            "uid": "prometheus"
          },
          "refId": "A"
        }
      ],
      "title": "System",
      "type": "row"
    },
    {
      "collapsed": true,
      "datasource": {
        "type": "prometheus",
        "uid": "prometheus"
      },
      "gridPos": {
        "h": 1,
        "w": 24,
        "x": 0,
        "y": 1
      },
      "id": 28,
      "panels": [
        {
          "datasource": {
            "type": "prometheus",
            "uid": "prometheus"
          },
          "fieldConfig": {
            "defaults": {
              "color": {
                "mode": "thresholds"
              },
              "mappings": [],
              "thresholds": {
                "mode": "absolute",
                "steps": [
                  {
                    "color": "green"
                  },
                  {
                    "color": "red",
                    "value": 80
                  }
                ]
              }
            },
            "overrides": []
          },
          "gridPos": {
            "h": 8,
            "w": 12,
            "x": 0,
            "y": 2
          },
          "id": 32,
          "options": {
            "colorMode": "value",
            "graphMode": "area",
            "justifyMode": "auto",
            "orientation": "auto",
            "reduceOptions": {
              "calcs": ["lastNotNull"],
              "fields": "",
              "values": false
            },
            "text": {},
            "textMode": "auto"
          },
          "pluginVersion": "9.0.2",
          "targets": [
            {
              "datasource": {
                "type": "prometheus",
                "uid": "prometheus"
              },
              "exemplar": true,
              "expr": "sum(cs_alerts)",
              "interval": "",
              "legendFormat": "",
              "refId": "A"
            }
          ],
          "title": "Alerts Count",
          "type": "stat"
        },
        {
          "datasource": {
            "type": "prometheus",
            "uid": "prometheus"
          },
          "fieldConfig": {
            "defaults": {
              "color": {
                "mode": "palette-classic"
              },
              "custom": {
                "axisLabel": "",
                "axisPlacement": "auto",
                "barAlignment": 0,
                "drawStyle": "line",
                "fillOpacity": 0,
                "gradientMode": "none",
                "hideFrom": {
                  "legend": false,
                  "tooltip": false,
                  "viz": false
                },
                "lineInterpolation": "linear",
                "lineWidth": 1,
                "pointSize": 5,
                "scaleDistribution": {
                  "type": "linear"
                },
                "showPoints": "auto",
                "spanNulls": false,
                "stacking": {
                  "group": "A",
                  "mode": "none"
                },
                "thresholdsStyle": {
                  "mode": "off"
                }
              },
              "mappings": [],
              "thresholds": {
                "mode": "absolute",
                "steps": [
                  {
                    "color": "green"
                  },
                  {
                    "color": "red",
                    "value": 80
                  }
                ]
              }
            },
            "overrides": []
          },
          "gridPos": {
            "h": 8,
            "w": 12,
            "x": 12,
            "y": 2
          },
          "id": 30,
          "options": {
            "legend": {
              "calcs": [],
              "displayMode": "list",
              "placement": "bottom"
            },
            "tooltip": {
              "mode": "single",
              "sort": "none"
            }
          },
          "targets": [
            {
              "datasource": {
                "type": "prometheus",
                "uid": "prometheus"
              },
              "exemplar": true,
              "expr": "cs_alerts{instance=\"$instance\"}",
              "interval": "",
              "legendFormat": "{{reason}}",
              "refId": "A"
            }
          ],
          "title": "Alerts per Scenario",
          "type": "timeseries"
        }
      ],
      "targets": [
        {
          "datasource": {
            "type": "prometheus",
            "uid": "prometheus"
          },
          "refId": "A"
        }
      ],
      "title": "Alerts",
      "type": "row"
    },
    {
      "collapsed": true,
      "datasource": {
        "type": "prometheus",
        "uid": "prometheus"
      },
      "gridPos": {
        "h": 1,
        "w": 24,
        "x": 0,
        "y": 2
      },
      "id": 24,
      "panels": [
        {
          "aliasColors": {},
          "bars": false,
          "dashLength": 10,
          "dashes": false,
          "datasource": {
            "type": "prometheus",
            "uid": "prometheus"
          },
          "decimals": 1,
          "fieldConfig": {
            "defaults": {
              "links": []
            },
            "overrides": []
          },
          "fill": 1,
          "fillGradient": 0,
          "gridPos": {
            "h": 12,
            "w": 24,
            "x": 0,
            "y": 3
          },
          "hiddenSeries": false,
          "id": 2,
          "legend": {
            "alignAsTable": true,
            "avg": false,
            "current": false,
            "max": false,
            "min": false,
            "rightSide": true,
            "show": true,
            "sort": "total",
            "sortDesc": true,
            "total": true,
            "values": true
          },
          "lines": true,
          "linewidth": 1,
          "nullPointMode": "null",
          "options": {
            "alertThreshold": true
          },
          "percentage": false,
          "pluginVersion": "9.0.2",
          "pointradius": 2,
          "points": false,
          "renderer": "flot",
          "seriesOverrides": [],
          "spaceLength": 10,
          "stack": false,
          "steppedLine": false,
          "targets": [
            {
              "datasource": {
                "type": "prometheus",
                "uid": "prometheus"
              },
              "exemplar": true,
              "expr": "sum(increase(cs_filesource_hits_total{instance=\"$instance\"}[$__interval])) by (source)",
              "interval": "",
              "intervalFactor": 2,
              "legendFormat": "{{source}}",
              "refId": "A"
            },
            {
              "datasource": {
                "type": "prometheus",
                "uid": "prometheus"
              },
              "exemplar": true,
              "expr": "sum(increase(cs_journalctlsource_hits_total{instance=\"$instance\"}[$__interval])) by (source)",
              "hide": false,
              "interval": "",
              "legendFormat": "{{source}}",
              "refId": "B"
            },
            {
              "datasource": {
                "type": "prometheus",
                "uid": "prometheus"
              },
              "exemplar": true,
              "expr": "sum(increase(cs_cloudwatch_stream_hits_total{instance=\"$instance\"}[$__interval])) by (group, stream)",
              "hide": false,
              "interval": "",
              "legendFormat": "{{group}} - {{stream}}",
              "refId": "C"
            },
            {
              "datasource": {
                "type": "prometheus",
                "uid": "prometheus"
              },
              "exemplar": true,
              "expr": "sum(increase(cs_syslogsource_hits_total{instance=\"$instance\"}[$__interval])) by (source)",
              "hide": false,
              "interval": "",
              "legendFormat": "",
              "refId": "D"
            }
          ],
          "thresholds": [],
          "timeRegions": [],
          "title": "Acquisition",
          "tooltip": {
            "shared": true,
            "sort": 0,
            "value_type": "individual"
          },
          "transparent": true,
          "type": "graph",
          "xaxis": {
            "mode": "time",
            "show": true,
            "values": []
          },
          "yaxes": [
            {
              "format": "short",
              "logBase": 1,
              "show": true
            },
            {
              "format": "short",
              "logBase": 1,
              "show": true
            }
          ],
          "yaxis": {
            "align": false
          }
        },
        {
          "aliasColors": {},
          "bars": false,
          "dashLength": 10,
          "dashes": false,
          "datasource": {
            "type": "prometheus",
            "uid": "prometheus"
          },
          "decimals": 1,
          "fieldConfig": {
            "defaults": {
              "links": []
            },
            "overrides": []
          },
          "fill": 1,
          "fillGradient": 0,
          "gridPos": {
            "h": 11,
            "w": 12,
            "x": 0,
            "y": 15
          },
          "hiddenSeries": false,
          "id": 4,
          "legend": {
            "alignAsTable": true,
            "avg": false,
            "current": false,
            "max": false,
            "min": false,
            "rightSide": true,
            "show": true,
            "sort": "total",
            "sortDesc": true,
            "total": true,
            "values": true
          },
          "lines": true,
          "linewidth": 1,
          "nullPointMode": "null",
          "options": {
            "alertThreshold": true
          },
          "percentage": false,
          "pluginVersion": "9.0.2",
          "pointradius": 2,
          "points": false,
          "renderer": "flot",
          "seriesOverrides": [],
          "spaceLength": 10,
          "stack": false,
          "steppedLine": false,
          "targets": [
            {
              "datasource": {
                "type": "prometheus",
                "uid": "prometheus"
              },
              "expr": "sum(increase(cs_parser_hits_ok_total{instance=\"$instance\"}[$__interval])) by (source)",
              "interval": "",
              "intervalFactor": 2,
              "legendFormat": "{{source}}",
              "refId": "A"
            }
          ],
          "thresholds": [],
          "timeRegions": [],
          "title": "Parsed lines",
          "tooltip": {
            "shared": true,
            "sort": 0,
            "value_type": "individual"
          },
          "transparent": true,
          "type": "graph",
          "xaxis": {
            "mode": "time",
            "show": true,
            "values": []
          },
          "yaxes": [
            {
              "format": "short",
              "logBase": 1,
              "show": true
            },
            {
              "format": "short",
              "logBase": 1,
              "show": true
            }
          ],
          "yaxis": {
            "align": false
          }
        },
        {
          "aliasColors": {},
          "bars": false,
          "dashLength": 10,
          "dashes": false,
          "datasource": {
            "type": "prometheus",
            "uid": "prometheus"
          },
          "decimals": 1,
          "fieldConfig": {
            "defaults": {
              "links": []
            },
            "overrides": []
          },
          "fill": 1,
          "fillGradient": 0,
          "gridPos": {
            "h": 11,
            "w": 12,
            "x": 12,
            "y": 15
          },
          "hiddenSeries": false,
          "id": 6,
          "legend": {
            "alignAsTable": true,
            "avg": false,
            "current": false,
            "max": false,
            "min": false,
            "rightSide": true,
            "show": true,
            "sort": "total",
            "sortDesc": true,
            "total": true,
            "values": true
          },
          "lines": true,
          "linewidth": 1,
          "nullPointMode": "null",
          "options": {
            "alertThreshold": true
          },
          "percentage": false,
          "pluginVersion": "9.0.2",
          "pointradius": 2,
          "points": false,
          "renderer": "flot",
          "seriesOverrides": [],
          "spaceLength": 10,
          "stack": false,
          "steppedLine": false,
          "targets": [
            {
              "datasource": {
                "type": "prometheus",
                "uid": "prometheus"
              },
              "expr": "sum(increase(cs_parser_hits_ko_total{instance=\"$instance\"}[$__interval])) by (source)",
              "interval": "",
              "intervalFactor": 2,
              "legendFormat": "{{source}}",
              "refId": "A"
            }
          ],
          "thresholds": [],
          "timeRegions": [],
          "title": "Unparsed lines",
          "tooltip": {
            "shared": true,
            "sort": 0,
            "value_type": "individual"
          },
          "transparent": true,
          "type": "graph",
          "xaxis": {
            "mode": "time",
            "show": true,
            "values": []
          },
          "yaxes": [
            {
              "format": "short",
              "logBase": 1,
              "show": true
            },
            {
              "format": "short",
              "logBase": 1,
              "show": true
            }
          ],
          "yaxis": {
            "align": false
          }
        },
        {
          "datasource": {
            "type": "prometheus",
            "uid": "prometheus"
          },
          "fieldConfig": {
            "defaults": {
              "color": {
                "mode": "thresholds"
              },
              "mappings": [],
              "thresholds": {
                "mode": "absolute",
                "steps": [
                  {
                    "color": "green",
                    "value": null
                  },
                  {
                    "color": "red",
                    "value": 80
                  }
                ]
              }
            },
            "overrides": []
          },
          "gridPos": {
            "h": 12,
            "w": 12,
            "x": 0,
            "y": 26
          },
          "id": 34,
          "options": {
            "displayMode": "gradient",
            "minVizHeight": 10,
            "minVizWidth": 0,
            "orientation": "auto",
            "reduceOptions": {
              "calcs": ["lastNotNull"],
              "fields": "",
              "values": false
            },
            "showUnfilled": true
          },
          "pluginVersion": "9.0.2",
          "targets": [
            {
              "datasource": {
                "type": "prometheus",
                "uid": "prometheus"
              },
              "editorMode": "code",
              "exemplar": true,
              "expr": "sum(rate(cs_parsing_time_seconds_bucket{instance=\"$instance\", type=\"$datasource_type\", source=\"$source\"}[$__rate_interval])) by (le)",
              "format": "heatmap",
              "legendFormat": "{{le}}",
              "range": true,
              "refId": "A"
            }
          ],
          "title": "Parsing time",
          "type": "heatmap"
        }
      ],
      "targets": [
        {
          "datasource": {
            "type": "prometheus",
            "uid": "prometheus"
          },
          "refId": "A"
        }
      ],
      "title": "Parsing",
      "type": "row"
    },
    {
      "collapsed": true,
      "datasource": {
        "type": "prometheus",
        "uid": "prometheus"
      },
      "gridPos": {
        "h": 1,
        "w": 24,
        "x": 0,
        "y": 3
      },
      "id": 26,
      "panels": [
        {
          "aliasColors": {},
          "bars": false,
          "dashLength": 10,
          "dashes": false,
          "datasource": {
            "type": "prometheus",
            "uid": "prometheus"
          },
          "decimals": 1,
          "fieldConfig": {
            "defaults": {
              "links": []
            },
            "overrides": []
          },
          "fill": 1,
          "fillGradient": 0,
          "gridPos": {
            "h": 8,
            "w": 24,
            "x": 0,
            "y": 4
          },
          "hiddenSeries": false,
          "id": 8,
          "legend": {
            "alignAsTable": true,
            "avg": false,
            "current": false,
            "max": false,
            "min": false,
            "rightSide": true,
            "show": true,
            "sort": "total",
            "sortDesc": true,
            "total": true,
            "values": true
          },
          "lines": true,
          "linewidth": 1,
          "nullPointMode": "null",
          "options": {
            "alertThreshold": true
          },
          "percentage": false,
          "pluginVersion": "9.0.2",
          "pointradius": 2,
          "points": false,
          "renderer": "flot",
          "seriesOverrides": [],
          "spaceLength": 10,
          "stack": false,
          "steppedLine": false,
          "targets": [
            {
              "datasource": {
                "type": "prometheus",
                "uid": "prometheus"
              },
              "expr": "sum(cs_buckets{instance=\"$instance\"}) by (name)",
              "interval": "",
              "legendFormat": "{{name}}",
              "refId": "A"
            }
          ],
          "thresholds": [],
          "timeRegions": [],
          "title": "Bucket Timeline",
          "tooltip": {
            "shared": true,
            "sort": 0,
            "value_type": "individual"
          },
          "transparent": true,
          "type": "graph",
          "xaxis": {
            "mode": "time",
            "show": true,
            "values": []
          },
          "yaxes": [
            {
              "format": "short",
              "logBase": 1,
              "show": true
            },
            {
              "format": "short",
              "logBase": 1,
              "show": true
            }
          ],
          "yaxis": {
            "align": false
          }
        },
        {
          "aliasColors": {},
          "bars": false,
          "dashLength": 10,
          "dashes": false,
          "datasource": {
            "type": "prometheus",
            "uid": "prometheus"
          },
          "decimals": 1,
          "fieldConfig": {
            "defaults": {
              "links": []
            },
            "overrides": []
          },
          "fill": 1,
          "fillGradient": 0,
          "gridPos": {
            "h": 9,
            "w": 24,
            "x": 0,
            "y": 12
          },
          "hiddenSeries": false,
          "id": 12,
          "legend": {
            "alignAsTable": true,
            "avg": false,
            "current": false,
            "max": false,
            "min": false,
            "rightSide": true,
            "show": true,
            "sort": "total",
            "sortDesc": true,
            "total": true,
            "values": true
          },
          "lines": true,
          "linewidth": 1,
          "nullPointMode": "null",
          "options": {
            "alertThreshold": true
          },
          "percentage": false,
          "pluginVersion": "9.0.2",
          "pointradius": 2,
          "points": false,
          "renderer": "flot",
          "seriesOverrides": [],
          "spaceLength": 10,
          "stack": false,
          "steppedLine": false,
          "targets": [
            {
              "datasource": {
                "type": "prometheus",
                "uid": "prometheus"
              },
              "expr": "sum(increase(cs_bucket_created_total{instance=\"$instance\"}[$__interval])) by (name)",
              "interval": "",
              "intervalFactor": 2,
              "legendFormat": "{{name}}",
              "refId": "A"
            }
          ],
          "thresholds": [],
          "timeRegions": [],
          "title": "Buckets creation",
          "tooltip": {
            "shared": true,
            "sort": 0,
            "value_type": "individual"
          },
          "type": "graph",
          "xaxis": {
            "mode": "time",
            "show": true,
            "values": []
          },
          "yaxes": [
            {
              "format": "short",
              "logBase": 1,
              "show": true
            },
            {
              "format": "short",
              "logBase": 1,
              "show": true
            }
          ],
          "yaxis": {
            "align": false
          }
        },
        {
          "aliasColors": {},
          "bars": false,
          "dashLength": 10,
          "dashes": false,
          "datasource": {
            "type": "prometheus",
            "uid": "prometheus"
          },
          "decimals": 1,
          "fieldConfig": {
            "defaults": {
              "links": []
            },
            "overrides": []
          },
          "fill": 1,
          "fillGradient": 0,
          "gridPos": {
            "h": 8,
            "w": 24,
            "x": 0,
            "y": 21
          },
          "hiddenSeries": false,
          "id": 11,
          "legend": {
            "alignAsTable": true,
            "avg": false,
            "current": false,
            "max": false,
            "min": false,
            "rightSide": true,
            "show": true,
            "sort": "total",
            "sortDesc": true,
            "total": true,
            "values": true
          },
          "lines": true,
          "linewidth": 1,
          "nullPointMode": "null",
          "options": {
            "alertThreshold": true
          },
          "percentage": false,
          "pluginVersion": "9.0.2",
          "pointradius": 2,
          "points": false,
          "renderer": "flot",
          "seriesOverrides": [],
          "spaceLength": 10,
          "stack": false,
          "steppedLine": false,
          "targets": [
            {
              "datasource": {
                "type": "prometheus",
                "uid": "prometheus"
              },
              "expr": "sum(increase(cs_bucket_overflowed_total{instance=\"$instance\"}[$__interval])) by (name)",
              "interval": "",
              "intervalFactor": 2,
              "legendFormat": "{{name}}",
              "refId": "A"
            }
          ],
          "thresholds": [],
          "timeRegions": [],
          "title": "Buckets overflow",
          "tooltip": {
            "shared": true,
            "sort": 0,
            "value_type": "individual"
          },
          "transparent": true,
          "type": "graph",
          "xaxis": {
            "mode": "time",
            "show": true,
            "values": []
          },
          "yaxes": [
            {
              "format": "short",
              "logBase": 1,
              "show": true
            },
            {
              "format": "short",
              "logBase": 1,
              "show": true
            }
          ],
          "yaxis": {
            "align": false
          }
        },
        {
          "aliasColors": {},
          "bars": false,
          "dashLength": 10,
          "dashes": false,
          "datasource": {
            "type": "prometheus",
            "uid": "prometheus"
          },
          "decimals": 1,
          "fieldConfig": {
            "defaults": {
              "links": []
            },
            "overrides": []
          },
          "fill": 1,
          "fillGradient": 0,
          "gridPos": {
            "h": 8,
            "w": 24,
            "x": 0,
            "y": 29
          },
          "hiddenSeries": false,
          "id": 14,
          "legend": {
            "alignAsTable": true,
            "avg": false,
            "current": false,
            "max": false,
            "min": false,
            "rightSide": true,
            "show": true,
            "sort": "total",
            "sortDesc": true,
            "total": true,
            "values": true
          },
          "lines": true,
          "linewidth": 1,
          "nullPointMode": "null",
          "options": {
            "alertThreshold": true
          },
          "percentage": false,
          "pluginVersion": "9.0.2",
          "pointradius": 2,
          "points": false,
          "renderer": "flot",
          "seriesOverrides": [],
          "spaceLength": 10,
          "stack": false,
          "steppedLine": false,
          "targets": [
            {
              "datasource": {
                "type": "prometheus",
                "uid": "prometheus"
              },
              "expr": "sum(increase(cs_bucket_underflowed_total{instance=\"$instance\"}[$__interval])) by (name)",
              "interval": "",
              "intervalFactor": 2,
              "legendFormat": "{{name}}",
              "refId": "A"
            }
          ],
          "thresholds": [],
          "timeRegions": [],
          "title": "Buckets underflow",
          "tooltip": {
            "shared": true,
            "sort": 0,
            "value_type": "individual"
          },
          "transparent": true,
          "type": "graph",
          "xaxis": {
            "mode": "time",
            "show": true,
            "values": []
          },
          "yaxes": [
            {
              "format": "short",
              "logBase": 1,
              "show": true
            },
            {
              "format": "short",
              "logBase": 1,
              "show": true
            }
          ],
          "yaxis": {
            "align": false
          }
        },
        {
          "datasource": {
            "type": "prometheus",
            "uid": "prometheus"
          },
          "fieldConfig": {
            "defaults": {
              "color": {
                "mode": "thresholds"
              },
              "mappings": [],
              "thresholds": {
                "mode": "absolute",
                "steps": [
                  {
                    "color": "green",
                    "value": null
                  },
                  {
                    "color": "red",
                    "value": 80
                  }
                ]
              }
            },
            "overrides": []
          },
          "gridPos": {
            "h": 12,
            "w": 12,
            "x": 0,
            "y": 37
          },
          "id": 35,
          "options": {
            "displayMode": "gradient",
            "minVizHeight": 10,
            "minVizWidth": 0,
            "orientation": "auto",
            "reduceOptions": {
              "calcs": ["lastNotNull"],
              "fields": "",
              "values": false
            },
            "showUnfilled": true
          },
          "pluginVersion": "9.0.2",
          "targets": [
            {
              "datasource": {
                "type": "prometheus",
                "uid": "prometheus"
              },
              "editorMode": "code",
              "exemplar": true,
              "expr": "sum(rate(cs_bucket_pour_seconds_bucket{instance=\"$instance\", type=\"$datasource_type\", source=\"$source\"}[$__rate_interval])) by (le)",
              "format": "heatmap",
              "legendFormat": "{{le}}",
              "range": true,
              "refId": "A"
            }
          ],
          "title": "Bucket pour time",
          "type": "heatmap"
        }
      ],
      "targets": [
        {
          "datasource": {
            "type": "prometheus",
            "uid": "prometheus"
          },
          "refId": "A"
        }
      ],
      "title": "Buckets",
      "type": "row"
    }
  ],
  "refresh": false,
  "schemaVersion": 36,
  "style": "dark",
  "tags": [],
  "templating": {
    "list": [
      {
        "current": {},
        "datasource": {
          "type": "prometheus",
          "uid": "prometheus"
        },
        "definition": "label_values(cs_info, instance)",
        "hide": 0,
        "includeAll": false,
        "label": "instance",
        "multi": false,
        "name": "instance",
        "options": [],
        "query": {
          "query": "label_values(cs_info, instance)",
          "refId": "Prometheus-instance-Variable-Query"
        },
        "refresh": 1,
        "regex": "",
        "skipUrlSync": false,
        "sort": 1,
        "tagValuesQuery": "",
        "tagsQuery": "",
        "type": "query",
        "useTags": false
      },
      {
        "current": {},
        "datasource": {
          "type": "prometheus",
          "uid": "prometheus"
        },
        "definition": "label_values(cs_parsing_time_seconds_bucket{instance=\"$instance\"}, type)",
        "hide": 0,
        "includeAll": false,
        "multi": false,
        "name": "datasource_type",
        "options": [],
        "query": {
          "query": "label_values(cs_parsing_time_seconds_bucket{instance=\"$instance\"}, type)",
          "refId": "StandardVariableQuery"
        },
        "refresh": 1,
        "regex": "",
        "skipUrlSync": false,
        "sort": 0,
        "type": "query"
      },
      {
        "current": {},
        "datasource": {
          "type": "prometheus",
          "uid": "prometheus"
        },
        "definition": "label_values(cs_parsing_time_seconds_bucket{instance=\"$instance\", type=\"$datasource_type\"}, source)",
        "hide": 0,
        "includeAll": false,
        "multi": false,
        "name": "source",
        "options": [],
        "query": {
          "query": "label_values(cs_parsing_time_seconds_bucket{instance=\"$instance\", type=\"$datasource_type\"}, source)",
          "refId": "StandardVariableQuery"
        },
        "refresh": 1,
        "regex": "",
        "skipUrlSync": false,
        "sort": 0,
        "type": "query"
      }
    ]
  },
  "time": {
    "from": "now-15m",
    "to": "now"
  },
  "timepicker": {
    "refresh_intervals": ["5s", "10s", "30s", "1m", "5m", "15m", "30m", "1h", "2h", "1d"]
  },
  "timezone": "",
  "title": "Crowdsec Details per instance",
  "uid": "crowdsec-details",
  "version": 7,
  "weekStart": ""
}
